nbdistributed/__init__.py
nbdistributed/communication.py
nbdistributed/magic.py
nbdistributed/process_manager.py
nbdistributed/worker.py
nbdistributed-0.1.0.dist-info/METADATA
nbdistributed-0.1.0.dist-info/WHEEL
nbdistributed-0.1.0.dist-info/entry_points.txt
nbdistributed-0.1.0.dist-info/licenses/LICENSE
nbdistributed-0.1.0.dist-info/RECORD
